ankylosaurus/__init__.py
ankylosaurus/database/__init__.py
ankylosaurus/database/models.py
ankylosaurus/database/wrapper.py
ankylosaurus-0.7.dist-info/LICENSE
ankylosaurus-0.7.dist-info/METADATA
ankylosaurus-0.7.dist-info/WHEEL
ankylosaurus-0.7.dist-info/top_level.txt
ankylosaurus-0.7.dist-info/RECORD
