Metadata-Version: 2.1
Name: ankylosaurus
Version: 0.7
Summary: Various utils.
Home-page: UNKNOWN
Author: Matteo Giani
Author-email: matteo.giani.87@gmail.com
License: UNKNOWN
Platform: UNKNOWN
Classifier: Programming Language :: Python :: 3.6
Requires-Python: >=3.6
Requires-Dist: sqlalchemy
Requires-Dist: imageio
